sshx/__init__.py
sshx/account.py
sshx/cfg.py
sshx/const.py
sshx/sshwrap.py
sshx/sshx.py
sshx/sshx_forward.py
sshx/sshx_scp.py
sshx/tokenizer.py
sshx/utils.py
sshx/tests/__init__.py
sshx/tests/test_account.py
sshx/tests/test_command.py
sshx/tests/test_config.py
sshx/tests/test_functional.py
sshx/tests/test_tokenizer.py
sshx/tests/test_utils.py
sshx-0.33.5.dist-info/LICENSE
sshx-0.33.5.dist-info/METADATA
sshx-0.33.5.dist-info/WHEEL
sshx-0.33.5.dist-info/entry_points.txt
sshx-0.33.5.dist-info/top_level.txt
sshx-0.33.5.dist-info/RECORD
