Metadata-Version: 2.1
Name: sshx
Version: 0.33.5
Summary: SSH eXtensions
Home-page: https://github.com/WqyJh/sshx
Author: wqy
Author-email: qiyingwangwqy@gmail.com
License: GNU General Public License v3
Keywords: ssh,pexpect,socks5
Platform: UNKNOWN
Classifier: Operating System :: OS Independent
Classifier: Programming Language :: Python :: 3
Classifier: Programming Language :: Python :: 3.5
Classifier: Programming Language :: Python :: 3.6
Classifier: Programming Language :: Python :: 3.7
Classifier: Programming Language :: Python :: 3.8
Requires-Dist: itsdangerous
Requires-Dist: pexpect
Requires-Dist: click
Requires-Dist: lazy-object-proxy
Requires-Dist: future-fstrings
